<?xml version="1.0" encoding="UTF-8"?>
<!DOCTYPE plist PUBLIC "-//Apple//DTD PLIST 1.0//EN" "http://www.apple.com/DTDs/PropertyList-1.0.dtd"/>

<plist version="1.0">
    <dict>
        <key>ROOT</key>
        <array>
            <dict>
                <key>id</key>
                <string>98</string>
                <key>children</key>
                <array>
                    <string>3158</string>
                    <string>3164</string>
                    <string>3161</string>
                </array>
            </dict>
            <dict>
                <key>id</key>
                <string>100</string>
                <key>Music</key>
                <dict>
                    <key>value</key>
                    <string>3217</string>
                </dict>
                <key>children</key>
                <array>
                    <string>1912</string>
                    <string>1925</string>
                    <string>2111</string>
                    <string>2153</string>
                    <string>2710</string>
                    <string>2712</string>
                </array>
            </dict>
            <dict>
                <key>id</key>
                <string>2113</string>
                <key>children</key>
                <array>
                    <string>2114</string>
                    <string>2119</string>
                    <string>2120</string>
                    <string>2131</string>
                    <string>3191</string>
                    <string>3208</string>
                    <string>2138</string>
                </array>
            </dict>
            <dict>
                <key>id</key>
                <string>2124</string>
                <key>children</key>
                <array>
                    <string>2125</string>
                    <string>2126</string>
                </array>
            </dict>
            <dict>
                <key>id</key>
                <string>2133</string>
                <key>children</key>
                <array>
                    <string>2134</string>
                    <string>2135</string>
                </array>
            </dict>
            <dict>
                <key>id</key>
                <string>2140</string>
                <key>children</key>
                <array>
                    <string>2141</string>
                    <string>2144</string>
                    <string>2147</string>
                    <string>2150</string>
                </array>
            </dict>
            <dict>
                <key>id</key>
                <string>2152</string>
                <key>children</key>
                <array>
                    <string>2154</string>
                    <string>2157</string>
                    <string>2160</string>
                    <string>2161</string>
                </array>
            </dict>
            <dict>
                <key>id</key>
                <string>2194</string>
                <key>children</key>
                <array/>
            </dict>
        </array>
    </dict>
</plist>
