<?xml version="1.0" encoding="UTF-8"?>
<!DOCTYPE plist PUBLIC "-//Apple//DTD PLIST 1.0//EN" "http://www.apple.com/DTDs/PropertyList-1.0.dtd"/>

<plist version="1.0">
    <dict>
        <key>ROOT</key>
        <array>
            <dict>
                <key>id</key>
                <string>3311</string>
                <key>Asset</key>
                <dict>
                    <key>value</key>
                    <string>3303</string>
                </dict>
            </dict>
            <dict>
                <key>id</key>
                <string>3313</string>
                <key>Asset</key>
                <dict>
                    <key>value</key>
                    <string>3303</string>
                </dict>
            </dict>
            <dict>
                <key>id</key>
                <string>3315</string>
                <key>Asset</key>
                <dict>
                    <key>value</key>
                    <string>3303</string>
                </dict>
            </dict>
            <dict>
                <key>id</key>
                <string>3318</string>
                <key>Asset</key>
                <dict>
                    <key>value</key>
                    <string>3303</string>
                </dict>
            </dict>
            <dict>
                <key>id</key>
                <string>3320</string>
                <key>Asset</key>
                <dict>
                    <key>value</key>
                    <string>3303</string>
                </dict>
            </dict>
            <dict>
                <key>id</key>
                <string>3322</string>
                <key>Asset</key>
                <dict>
                    <key>value</key>
                    <string>3303</string>
                </dict>
            </dict>
            <dict>
                <key>id</key>
                <string>3324</string>
                <key>Asset</key>
                <dict>
                    <key>value</key>
                    <string>3303</string>
                </dict>
            </dict>
            <dict>
                <key>id</key>
                <string>3326</string>
                <key>Asset</key>
                <dict>
                    <key>value</key>
                    <string>3303</string>
                </dict>
            </dict>
            <dict>
                <key>id</key>
                <string>3337</string>
                <key>Asset</key>
                <dict>
                    <key>value</key>
                    <string>3303</string>
                </dict>
            </dict>
            <dict>
                <key>id</key>
                <string>3339</string>
                <key>Asset</key>
                <dict>
                    <key>value</key>
                    <string>3303</string>
                </dict>
            </dict>
            <dict>
                <key>id</key>
                <string>3341</string>
                <key>Asset</key>
                <dict>
                    <key>value</key>
                    <string>3303</string>
                </dict>
            </dict>
            <dict>
                <key>id</key>
                <string>3463</string>
                <key>Asset</key>
                <dict>
                    <key>value</key>
                    <string>3303</string>
                </dict>
            </dict>
            <dict>
                <key>id</key>
                <string>3465</string>
                <key>Asset</key>
                <dict>
                    <key>value</key>
                    <string>3303</string>
                </dict>
            </dict>
            <dict>
                <key>id</key>
                <string>3467</string>
                <key>Asset</key>
                <dict>
                    <key>value</key>
                    <string>3303</string>
                </dict>
            </dict>
            <dict>
                <key>id</key>
                <string>3469</string>
                <key>Asset</key>
                <dict>
                    <key>value</key>
                    <string>3303</string>
                </dict>
            </dict>
            <dict>
                <key>id</key>
                <string>3475</string>
                <key>Asset</key>
                <dict>
                    <key>value</key>
                    <string>3303</string>
                </dict>
            </dict>
            <dict>
                <key>id</key>
                <string>3477</string>
                <key>Asset</key>
                <dict>
                    <key>value</key>
                    <string>3303</string>
                </dict>
            </dict>
            <dict>
                <key>id</key>
                <string>3479</string>
                <key>Asset</key>
                <dict>
                    <key>value</key>
                    <string>3303</string>
                </dict>
            </dict>
            <dict>
                <key>id</key>
                <string>3503</string>
                <key>Asset</key>
                <dict>
                    <key>value</key>
                    <string>3303</string>
                </dict>
            </dict>
            <dict>
                <key>id</key>
                <string>3505</string>
                <key>Asset</key>
                <dict>
                    <key>value</key>
                    <string>3303</string>
                </dict>
            </dict>
            <dict>
                <key>id</key>
                <string>3507</string>
                <key>Asset</key>
                <dict>
                    <key>value</key>
                    <string>3303</string>
                </dict>
            </dict>
            <dict>
                <key>id</key>
                <string>3509</string>
                <key>Asset</key>
                <dict>
                    <key>value</key>
                    <string>3303</string>
                </dict>
            </dict>
            <dict>
                <key>id</key>
                <string>3511</string>
                <key>Asset</key>
                <dict>
                    <key>value</key>
                    <string>3303</string>
                </dict>
            </dict>
            <dict>
                <key>id</key>
                <string>3513</string>
                <key>Asset</key>
                <dict>
                    <key>value</key>
                    <string>3303</string>
                </dict>
            </dict>
            <dict>
                <key>id</key>
                <string>3515</string>
                <key>Asset</key>
                <dict>
                    <key>value</key>
                    <string>3303</string>
                </dict>
            </dict>
            <dict>
                <key>id</key>
                <string>3517</string>
                <key>Asset</key>
                <dict>
                    <key>value</key>
                    <string>3303</string>
                </dict>
            </dict>
            <dict>
                <key>id</key>
                <string>3519</string>
                <key>Asset</key>
                <dict>
                    <key>value</key>
                    <string>3303</string>
                </dict>
            </dict>
            <dict>
                <key>id</key>
                <string>3521</string>
                <key>Asset</key>
                <dict>
                    <key>value</key>
                    <string>3303</string>
                </dict>
            </dict>
            <dict>
                <key>id</key>
                <string>3523</string>
                <key>Asset</key>
                <dict>
                    <key>value</key>
                    <string>3303</string>
                </dict>
            </dict>
            <dict>
                <key>id</key>
                <string>3525</string>
                <key>Asset</key>
                <dict>
                    <key>value</key>
                    <string>3303</string>
                </dict>
            </dict>
            <dict>
                <key>id</key>
                <string>3527</string>
                <key>Asset</key>
                <dict>
                    <key>value</key>
                    <string>3303</string>
                </dict>
            </dict>
            <dict>
                <key>id</key>
                <string>3529</string>
                <key>Asset</key>
                <dict>
                    <key>value</key>
                    <string>3303</string>
                </dict>
            </dict>
            <dict>
                <key>id</key>
                <string>3531</string>
                <key>Asset</key>
                <dict>
                    <key>value</key>
                    <string>3303</string>
                </dict>
            </dict>
            <dict>
                <key>id</key>
                <string>3533</string>
                <key>Asset</key>
                <dict>
                    <key>value</key>
                    <string>3303</string>
                </dict>
            </dict>
            <dict>
                <key>id</key>
                <string>3534</string>
                <key>Asset</key>
                <dict>
                    <key>value</key>
                    <string>3303</string>
                </dict>
            </dict>
            <dict>
                <key>id</key>
                <string>3538</string>
                <key>Asset</key>
                <dict>
                    <key>value</key>
                    <string>3303</string>
                </dict>
            </dict>
            <dict>
                <key>id</key>
                <string>3540</string>
                <key>Asset</key>
                <dict>
                    <key>value</key>
                    <string>3303</string>
                </dict>
            </dict>
            <dict>
                <key>id</key>
                <string>3542</string>
                <key>Asset</key>
                <dict>
                    <key>value</key>
                    <string>3303</string>
                </dict>
            </dict>
            <dict>
                <key>id</key>
                <string>3545</string>
                <key>Asset</key>
                <dict>
                    <key>value</key>
                    <string>3303</string>
                </dict>
            </dict>
            <dict>
                <key>id</key>
                <string>3547</string>
                <key>Asset</key>
                <dict>
                    <key>value</key>
                    <string>3303</string>
                </dict>
            </dict>
            <dict>
                <key>id</key>
                <string>3549</string>
                <key>Asset</key>
                <dict>
                    <key>value</key>
                    <string>3303</string>
                </dict>
            </dict>
            <dict>
                <key>id</key>
                <string>3551</string>
                <key>Asset</key>
                <dict>
                    <key>value</key>
                    <string>3303</string>
                </dict>
            </dict>
            <dict>
                <key>id</key>
                <string>3553</string>
                <key>Asset</key>
                <dict>
                    <key>value</key>
                    <string>3303</string>
                </dict>
            </dict>
            <dict>
                <key>id</key>
                <string>3555</string>
                <key>Asset</key>
                <dict>
                    <key>value</key>
                    <string>3303</string>
                </dict>
            </dict>
            <dict>
                <key>id</key>
                <string>3557</string>
                <key>Asset</key>
                <dict>
                    <key>value</key>
                    <string>3303</string>
                </dict>
            </dict>
            <dict>
                <key>id</key>
                <string>3559</string>
                <key>Asset</key>
                <dict>
                    <key>value</key>
                    <string>3303</string>
                </dict>
            </dict>
        </array>
    </dict>
</plist>
